{
 "mdmId": "C-31999-prod",
 "name": "ADD 2 Sides for $6.95",
 "id": "C-31999-prod",
 "customizable": false,
 "dname": [
  {
   "lang": "en-US",
   "value": "ADD 2 Sides for $6.95"
  }
 ],
 "shortDescription": [],
 "longDescription": [],
 "imageName": "https://images.ctfassets.net/crbk84xktnsl/2nPxqj0LvYh05LxIlkdGOh/b7fc4902ea42519023a027f9a3dc2c2b/Sides_2.png",
 "items": [
  {
   "mdmId": "I-31999",
   "id": "I-31999",
   "name": "ADD 2 Sides for $6.95",
   "size": null,
   "linkId": "42869",
   "url": "add-2-sides-for-695",
   "isPromo": false,
   "posId": "136073",
   "displayOrder": 0,
   "customizable": false,
   "dname": [
    {
     "lang": "en-US",
     "value": "ADD 2 Sides for $6.95"
    }
   ],
   "shortDescription": [
    {
     "lang": "en-US",
     "value": "ADD 2 Sides for $6.95"
    }
   ],
   "longDescription": [
    {
     "lang": "en-US",
     "value": "ADD 2 Sides for $6.95"
    }
   ],
   "imageName": [
    {
     "lang": "en-US",
     "value": "https://images.ctfassets.net/crbk84xktnsl/2nPxqj0LvYh05LxIlkdGOh/b7fc4902ea42519023a027f9a3dc2c2b/Sides_2.png"
    }
   ],
   "modgrps": [
    {
     "id": "91406",
     "name": "Add 2 Sides",
     "dname": [
      {
       "lang": "en-US",
       "value": "Add 2 Sides"
      }
     ],
     "min": 2,
     "max": 2,
     "shortDescription": [
      {
       "lang": "en-US",
       "value": "Add 2 Sides"
      }
     ],
     "longDescription": [
      {
       "lang": "en-US",
       "value": "Add 2 Sides"
      }
     ],
     "modifiers": [
      {
       "mdmId": "M-136010",
       "id": "M-136010",
       "name": "Large Chips",
       "size": "",
       "linkId": "mod:555928",
       "url": "large-chips",
       "isPromo": false,
       "posId": "136010",
       "displayOrder": 469,
       "customizable": false,
       "dname": [
        {
         "lang": "en-US",
         "value": "Large Chips"
        }
       ],
       "shortDescription": [
        {
         "lang": "en-US",
         "value": "Large Chips"
        }
       ],
       "longDescription": [
        {
         "lang": "en-US",
         "value": "Large Chips"
        }
       ],
       "imageName": [
        {
         "lang": "en-US",
         "value": "https://images.ctfassets.net/crbk84xktnsl/5oYGeN9nuG4pClVCe4Ntkk/470c7e32321b595e6acc68c8bddd53a2/Chips_lge.png"
        }
       ],
       "modgrps": [
        {
         "id": "91407",
         "name": "Modify Chips",
         "dname": [
          {
           "lang": "en-US",
           "value": "Modify Chips"
          }
         ],
         "min": 0,
         "max": 1,
         "shortDescription": [
          {
           "lang": "en-US",
           "value": "Modify Chips"
          }
         ],
         "longDescription": [
          {
           "lang": "en-US",
           "value": "Modify Chips"
          }
         ],
         "modifiers": [
          {
           "mdmId": "M-200031",
           "id": "M-200031",
           "name": "Extra Salt",
           "size": "",
           "linkId": "mod:554382",
           "url": "extra-salt",
           "isPromo": false,
           "posId": "200031",
           "displayOrder": 470,
           "customizable": true,
           "dname": [
            {
             "lang": "en-US",
             "value": "Extra Salt"
            }
           ],
           "shortDescription": [
            {
             "lang": "en-US",
             "value": "Extra Salt"
            }
           ],
           "longDescription": [
            {
             "lang": "en-US",
             "value": "Extra Salt"
            }
           ],
           "imageName": [
            {
             "lang": "en-US",
             "value": "https://images.ctfassets.net/crbk84xktnsl/3AfJV4aLAtIeB68Z7zB4Ff/fa811380ff7d978fdd9a5a15d6729148/Modifier_Salt.png"
            }
           ],
           "modgrps": [],
           "isHidden": false,
           "availability": [
            {
             "dayOfWeek": {
              "day": "EVERYDAY"
             },
             "availableHours": {
              "startTime": {
               "time": "0001"
              },
              "endTime": {
               "time": "2359"
              }
             },
             "price": 0
            }
           ],
           "effectiveStartDateTime": 0,
           "effectiveEndDateTime": 0,
           "additionalProperties": [],
           "defaultQuantity": 1,
           "isDefault": false,
           "max": 0,
           "content": {
            "entityId": "M-200031",
            "caloricValue": null,
            "image": {
             "mainImage": "https://images.ctfassets.net/crbk84xktnsl/3AfJV4aLAtIeB68Z7zB4Ff/fa811380ff7d978fdd9a5a15d6729148/Modifier_Salt.png",
             "secondaryImage": null,
             "tertiaryImage": null
            }
           }
          },
          {
           "mdmId": "M-200030",
           "id": "M-200030",
           "name": "No Salt",
           "size": "",
           "linkId": "mod:554383",
           "url": "no-salt",
           "isPromo": false,
           "posId": "200030",
           "displayOrder": 471,
           "customizable": true,
           "dname": [
            {
             "lang": "en-US",
             "value": "No Salt"
            }
           ],
           "shortDescription": [
            {
             "lang": "en-US",
             "value": "No Salt"
            }
           ],
           "longDescription": [
            {
             "lang": "en-US",
             "value": "No Salt"
            }
           ],
           "imageName": [
            {
             "lang": "en-US",
             "value": "https://images.ctfassets.net/crbk84xktnsl/2szW3dpmch2lJs8eIMjyOK/10d97b060f434f03cca661499597c6c5/Modifier_No_Salt.png"
            }
           ],
           "modgrps": [],
           "isHidden": false,
           "availability": [
            {
             "dayOfWeek": {
              "day": "EVERYDAY"
             },
             "availableHours": {
              "startTime": {
               "time": "0001"
              },
              "endTime": {
               "time": "2359"
              }
             },
             "price": 0
            }
           ],
           "effectiveStartDateTime": 0,
           "effectiveEndDateTime": 0,
           "additionalProperties": [],
           "defaultQuantity": 1,
           "isDefault": false,
           "max": 0,
           "content": {
            "entityId": "M-200030",
            "caloricValue": null,
            "image": {
             "mainImage": "https://images.ctfassets.net/crbk84xktnsl/2szW3dpmch2lJs8eIMjyOK/10d97b060f434f03cca661499597c6c5/Modifier_No_Salt.png",
             "secondaryImage": null,
             "tertiaryImage": null
            }
           }
          }
         ],
         "additionalProperties": [
          {
           "key": "peroptionmaximum",
           "value": "0"
          },
          {
           "key": "peroptionminimum",
           "value": "0"
          },
          {
           "key": "maxdistinctoptions",
           "value": "0"
          }
         ],
         "displayOrder": 0,
         "isHidden": false
        }
       ],
       "isHidden": false,
       "availability": [
        {
         "dayOfWeek": {
          "day": "EVERYDAY"
         },
         "availableHours": {
          "startTime": {
           "time": "0001"
          },
          "endTime": {
           "time": "2359"
          }
         },
         "price": 0
        }
       ],
       "effectiveStartDateTime": 0,
       "effectiveEndDateTime": 0,
       "additionalProperties": [
        {
         "key": "defaultreason",
         "value": "SELECTION"
        }
       ],
       "defaultQuantity": 1,
       "isDefault": true,
       "max": 0,
       "content": {
        "entityId": "M-136010",
        "caloricValue": "2431",
        "image": {
         "mainImage": "https://images.ctfassets.net/crbk84xktnsl/5oYGeN9nuG4pClVCe4Ntkk/470c7e32321b595e6acc68c8bddd53a2/Chips_lge.png",
         "secondaryImage": null,
         "tertiaryImage": null
        }
       }
      },
      {
       "mdmId": "M-136027",
       "id": "M-136027",
       "name": "Large Potato & Gravy",
       "size": "",
       "linkId": "mod:555923",
       "url": "large-potato-gravy",
       "isPromo": false,
       "posId": "136027",
       "displayOrder": 472,
       "customizable": false,
       "dname": [
        {
         "lang": "en-US",
         "value": "Large Potato & Gravy"
        }
       ],
       "shortDescription": [
        {
         "lang": "en-US",
         "value": "Large Potato & Gravy"
        }
       ],
       "longDescription": [
        {
         "lang": "en-US",
         "value": "Large Potato & Gravy"
        }
       ],
       "imageName": [
        {
         "lang": "en-US",
         "value": "https://images.ctfassets.net/crbk84xktnsl/2dxqC7cN4QHJtnI04aOHR6/dc2fb4a0416e41f18b0a11413b63aa75/Potato___Gravy_lge.png"
        }
       ],
       "modgrps": [],
       "isHidden": false,
       "availability": [
        {
         "dayOfWeek": {
          "day": "EVERYDAY"
         },
         "availableHours": {
          "startTime": {
           "time": "0001"
          },
          "endTime": {
           "time": "2359"
          }
         },
         "price": 0
        }
       ],
       "effectiveStartDateTime": 0,
       "effectiveEndDateTime": 0,
       "additionalProperties": [
        {
         "key": "defaultreason",
         "value": "SELECTION"
        }
       ],
       "defaultQuantity": 1,
       "isDefault": true,
       "max": 0,
       "content": {
        "entityId": "M-136027",
        "caloricValue": "1094",
        "image": {
         "mainImage": "https://images.ctfassets.net/crbk84xktnsl/2dxqC7cN4QHJtnI04aOHR6/dc2fb4a0416e41f18b0a11413b63aa75/Potato___Gravy_lge.png",
         "secondaryImage": null,
         "tertiaryImage": null
        }
       }
      },
      {
       "mdmId": "M-136045",
       "id": "M-136045",
       "name": "Large Coleslaw",
       "size": "",
       "linkId": "mod:555924",
       "url": "large-coleslaw",
       "isPromo": false,
       "posId": "136045",
       "displayOrder": 473,
       "customizable": false,
       "dname": [
        {
         "lang": "en-US",
         "value": "Large Coleslaw"
        }
       ],
       "shortDescription": [
        {
         "lang": "en-US",
         "value": "Large Coleslaw"
        }
       ],
       "longDescription": [
        {
         "lang": "en-US",
         "value": "Large Coleslaw"
        }
       ],
       "imageName": [
        {
         "lang": "en-US",
         "value": "https://images.ctfassets.net/crbk84xktnsl/4yCscBrUGTPYhR2eUn7YSf/a9bd4b7edeb2182aba0d62367e66be65/Coleslaw_lge.png"
        }
       ],
       "modgrps": [],
       "isHidden": false,
       "availability": [
        {
         "dayOfWeek": {
          "day": "EVERYDAY"
         },
         "availableHours": {
          "startTime": {
           "time": "0001"
          },
          "endTime": {
           "time": "2359"
          }
         },
         "price": 0
        }
       ],
       "effectiveStartDateTime": 0,
       "effectiveEndDateTime": 0,
       "additionalProperties": [],
       "defaultQuantity": 1,
       "isDefault": false,
       "max": 0,
       "content": {
        "entityId": "M-136045",
        "caloricValue": "1714",
        "image": {
         "mainImage": "https://images.ctfassets.net/crbk84xktnsl/4yCscBrUGTPYhR2eUn7YSf/a9bd4b7edeb2182aba0d62367e66be65/Coleslaw_lge.png",
         "secondaryImage": null,
         "tertiaryImage": null
        }
       }
      },
      {
       "mdmId": "M-136026",
       "id": "M-136026",
       "name": "Regular Gravy",
       "size": "",
       "linkId": "mod:555926",
       "url": "regular-gravy",
       "isPromo": false,
       "posId": "136026",
       "displayOrder": 474,
       "customizable": false,
       "dname": [
        {
         "lang": "en-US",
         "value": "Regular Gravy"
        }
       ],
       "shortDescription": [
        {
         "lang": "en-US",
         "value": "Regular Gravy"
        }
       ],
       "longDescription": [
        {
         "lang": "en-US",
         "value": "Regular Gravy"
        }
       ],
       "imageName": [
        {
         "lang": "en-US",
         "value": "https://images.ctfassets.net/crbk84xktnsl/DhijcDpBIfr1DgsPy1Wy0/b72880b780a18f090a4ca8000aae5cf5/Gravy_reg.png"
        }
       ],
       "modgrps": [],
       "isHidden": false,
       "availability": [
        {
         "dayOfWeek": {
          "day": "EVERYDAY"
         },
         "availableHours": {
          "startTime": {
           "time": "0001"
          },
          "endTime": {
           "time": "2359"
          }
         },
         "price": 0
        }
       ],
       "effectiveStartDateTime": 0,
       "effectiveEndDateTime": 0,
       "additionalProperties": [],
       "defaultQuantity": 1,
       "isDefault": false,
       "max": 0,
       "content": {
        "entityId": "M-136026",
        "caloricValue": "215",
        "image": {
         "mainImage": "https://images.ctfassets.net/crbk84xktnsl/DhijcDpBIfr1DgsPy1Wy0/b72880b780a18f090a4ca8000aae5cf5/Gravy_reg.png",
         "secondaryImage": null,
         "tertiaryImage": null
        }
       }
      },
      {
       "mdmId": "M-136047",
       "id": "M-136047",
       "name": "4 Dinner Rolls",
       "size": "",
       "linkId": "mod:555931",
       "url": "4-dinner-rolls",
       "isPromo": false,
       "posId": "136047",
       "displayOrder": 475,
       "customizable": false,
       "dname": [
        {
         "lang": "en-US",
         "value": "4 Dinner Rolls"
        }
       ],
       "shortDescription": [
        {
         "lang": "en-US",
         "value": "4 Dinner Rolls"
        }
       ],
       "longDescription": [
        {
         "lang": "en-US",
         "value": "4 Dinner Rolls"
        }
       ],
       "imageName": [
        {
         "lang": "en-US",
         "value": "https://images.ctfassets.net/crbk84xktnsl/4rofp5PSyCZPcfVoaGgZrN/c34690b54af325d921516cf9dbbeda22/Modifier_Dinner_Roll_4.png"
        }
       ],
       "modgrps": [],
       "isHidden": false,
       "availability": [
        {
         "dayOfWeek": {
          "day": "EVERYDAY"
         },
         "availableHours": {
          "startTime": {
           "time": "0001"
          },
          "endTime": {
           "time": "2359"
          }
         },
         "price": 0
        }
       ],
       "effectiveStartDateTime": 0,
       "effectiveEndDateTime": 0,
       "additionalProperties": [],
       "defaultQuantity": 1,
       "isDefault": false,
       "max": 0,
       "content": {
        "entityId": "M-136047",
        "caloricValue": "1840",
        "image": {
         "mainImage": "https://images.ctfassets.net/crbk84xktnsl/4rofp5PSyCZPcfVoaGgZrN/c34690b54af325d921516cf9dbbeda22/Modifier_Dinner_Roll_4.png",
         "secondaryImage": null,
         "tertiaryImage": null
        }
       }
      },
      {
       "mdmId": "M-141061",
       "id": "M-141061",
       "name": "1.25L Pepsi Max",
       "size": "",
       "linkId": "mod:555929",
       "url": "125l-pepsi-max",
       "isPromo": false,
       "posId": "141061",
       "displayOrder": 476,
       "customizable": false,
       "dname": [
        {
         "lang": "en-US",
         "value": "1.25L Pepsi Max"
        }
       ],
       "shortDescription": [
        {
         "lang": "en-US",
         "value": "1.25L Pepsi Max"
        }
       ],
       "longDescription": [
        {
         "lang": "en-US",
         "value": "1.25L Pepsi Max"
        }
       ],
       "imageName": [
        {
         "lang": "en-US",
         "value": "https://images.ctfassets.net/crbk84xktnsl/7fuVNYVcBPfOC9Jl9DsH1r/a0a3082815dea0bd3c8a92a519bb9753/Drink_Pepsi_Max_1.25L.png"
        }
       ],
       "modgrps": [],
       "isHidden": false,
       "availability": [
        {
         "dayOfWeek": {
          "day": "EVERYDAY"
         },
         "availableHours": {
          "startTime": {
           "time": "0001"
          },
          "endTime": {
           "time": "2359"
          }
         },
         "price": 0
        }
       ],
       "effectiveStartDateTime": 0,
       "effectiveEndDateTime": 0,
       "additionalProperties": [],
       "defaultQuantity": 1,
       "isDefault": false,
       "max": 0,
       "content": {
        "entityId": "M-141061",
        "caloricValue": "20",
        "image": {
         "mainImage": "https://images.ctfassets.net/crbk84xktnsl/7fuVNYVcBPfOC9Jl9DsH1r/a0a3082815dea0bd3c8a92a519bb9753/Drink_Pepsi_Max_1.25L.png",
         "secondaryImage": null,
         "tertiaryImage": null
        }
       }
      },
      {
       "mdmId": "M-141011",
       "id": "M-141011",
       "name": "1.25L Pepsi",
       "size": "",
       "linkId": "mod:555930",
       "url": "125l-pepsi",
       "isPromo": false,
       "posId": "141011",
       "displayOrder": 477,
       "customizable": false,
       "dname": [
        {
         "lang": "en-US",
         "value": "1.25L Pepsi"
        }
       ],
       "shortDescription": [
        {
         "lang": "en-US",
         "value": "1.25L Pepsi"
        }
       ],
       "longDescription": [
        {
         "lang": "en-US",
         "value": "1.25L Pepsi"
        }
       ],
       "imageName": [
        {
         "lang": "en-US",
         "value": "https://images.ctfassets.net/crbk84xktnsl/1FPPbRrAU8bn4YmOPrDSmW/d4352b31e980aa89f82d09c263853daf/Drink_Pepsi_1.25L.png"
        }
       ],
       "modgrps": [],
       "isHidden": false,
       "availability": [
        {
         "dayOfWeek": {
          "day": "EVERYDAY"
         },
         "availableHours": {
          "startTime": {
           "time": "0001"
          },
          "endTime": {
           "time": "2359"
          }
         },
         "price": 0
        }
       ],
       "effectiveStartDateTime": 0,
       "effectiveEndDateTime": 0,
       "additionalProperties": [],
       "defaultQuantity": 1,
       "isDefault": false,
       "max": 0,
       "content": {
        "entityId": "M-141011",
        "caloricValue": "2323",
        "image": {
         "mainImage": "https://images.ctfassets.net/crbk84xktnsl/1FPPbRrAU8bn4YmOPrDSmW/d4352b31e980aa89f82d09c263853daf/Drink_Pepsi_1.25L.png",
         "secondaryImage": null,
         "tertiaryImage": null
        }
       }
      },
      {
       "mdmId": "M-141044",
       "id": "M-141044",
       "name": "1.25L 7Up",
       "size": "",
       "linkId": "mod:555925",
       "url": "125l-7up",
       "isPromo": false,
       "posId": "141044",
       "displayOrder": 478,
       "customizable": false,
       "dname": [
        {
         "lang": "en-US",
         "value": "1.25L 7Up"
        }
       ],
       "shortDescription": [
        {
         "lang": "en-US",
         "value": "1.25L 7Up"
        }
       ],
       "longDescription": [
        {
         "lang": "en-US",
         "value": "1.25L 7Up"
        }
       ],
       "imageName": [
        {
         "lang": "en-US",
         "value": "https://images.ctfassets.net/crbk84xktnsl/6cUNLAD5ucrN7nYkoX5Ht1/dd58e2da3b779b790dcd2c9065712eb5/Drink_7up_1.25L.png"
        }
       ],
       "modgrps": [],
       "isHidden": false,
       "availability": [
        {
         "dayOfWeek": {
          "day": "EVERYDAY"
         },
         "availableHours": {
          "startTime": {
           "time": "0001"
          },
          "endTime": {
           "time": "2359"
          }
         },
         "price": 0
        }
       ],
       "effectiveStartDateTime": 0,
       "effectiveEndDateTime": 0,
       "additionalProperties": [],
       "defaultQuantity": 1,
       "isDefault": false,
       "max": 0,
       "content": {
        "entityId": "M-141044",
        "caloricValue": "2244",
        "image": {
         "mainImage": "https://images.ctfassets.net/crbk84xktnsl/6cUNLAD5ucrN7nYkoX5Ht1/dd58e2da3b779b790dcd2c9065712eb5/Drink_7up_1.25L.png",
         "secondaryImage": null,
         "tertiaryImage": null
        }
       }
      },
      {
       "mdmId": "M-141026",
       "id": "M-141026",
       "name": "1.25L Mountain Dew",
       "size": "",
       "linkId": "mod:555927",
       "url": "125l-mountain-dew",
       "isPromo": false,
       "posId": "141026",
       "displayOrder": 479,
       "customizable": false,
       "dname": [
        {
         "lang": "en-US",
         "value": "1.25L Mountain Dew"
        }
       ],
       "shortDescription": [
        {
         "lang": "en-US",
         "value": "1.25L Mountain Dew"
        }
       ],
       "longDescription": [
        {
         "lang": "en-US",
         "value": "1.25L Mountain Dew"
        }
       ],
       "imageName": [
        {
         "lang": "en-US",
         "value": "https://images.ctfassets.net/crbk84xktnsl/69IQ9UhjUbH3495HzLw6vc/5331f48b435b3f5e5b2e29a1acbf1bc5/Drink_Mt_Dew_1.25L.png"
        }
       ],
       "modgrps": [],
       "isHidden": false,
       "availability": [
        {
         "dayOfWeek": {
          "day": "EVERYDAY"
         },
         "availableHours": {
          "startTime": {
           "time": "0001"
          },
          "endTime": {
           "time": "2359"
          }
         },
         "price": 0
        }
       ],
       "effectiveStartDateTime": 0,
       "effectiveEndDateTime": 0,
       "additionalProperties": [],
       "defaultQuantity": 1,
       "isDefault": false,
       "max": 0,
       "content": {
        "entityId": "M-141026",
        "caloricValue": "2468",
        "image": {
         "mainImage": "https://images.ctfassets.net/crbk84xktnsl/69IQ9UhjUbH3495HzLw6vc/5331f48b435b3f5e5b2e29a1acbf1bc5/Drink_Mt_Dew_1.25L.png",
         "secondaryImage": null,
         "tertiaryImage": null
        }
       }
      },
      {
       "mdmId": "M-141032",
       "id": "M-141032",
       "name": "1.25L Solo",
       "size": "",
       "linkId": "mod:555921",
       "url": "125l-solo",
       "isPromo": false,
       "posId": "141032",
       "displayOrder": 480,
       "customizable": false,
       "dname": [
        {
         "lang": "en-US",
         "value": "1.25L Solo"
        }
       ],
       "shortDescription": [
        {
         "lang": "en-US",
         "value": "1.25L Solo"
        }
       ],
       "longDescription": [
        {
         "lang": "en-US",
         "value": "1.25L Solo"
        }
       ],
       "imageName": [
        {
         "lang": "en-US",
         "value": "https://images.ctfassets.net/crbk84xktnsl/2F0T5pAEeV5n64zejhuwPG/2432bf729da2ca0e43bae6300c2e9da8/Drink_Solo_1.25L.png"
        }
       ],
       "modgrps": [],
       "isHidden": false,
       "availability": [
        {
         "dayOfWeek": {
          "day": "EVERYDAY"
         },
         "availableHours": {
          "startTime": {
           "time": "0001"
          },
          "endTime": {
           "time": "2359"
          }
         },
         "price": 0
        }
       ],
       "effectiveStartDateTime": 0,
       "effectiveEndDateTime": 0,
       "additionalProperties": [],
       "defaultQuantity": 1,
       "isDefault": false,
       "max": 0,
       "content": {
        "entityId": "M-141032",
        "caloricValue": "2496",
        "image": {
         "mainImage": "https://images.ctfassets.net/crbk84xktnsl/2F0T5pAEeV5n64zejhuwPG/2432bf729da2ca0e43bae6300c2e9da8/Drink_Solo_1.25L.png",
         "secondaryImage": null,
         "tertiaryImage": null
        }
       }
      },
      {
       "mdmId": "M-141017",
       "id": "M-141017",
       "name": "1.25L Sunkist No Sugar",
       "size": "",
       "linkId": "mod:556147",
       "url": "125l-sunkist-no-sugar",
       "isPromo": false,
       "posId": "141017",
       "displayOrder": 481,
       "customizable": false,
       "dname": [
        {
         "lang": "en-US",
         "value": "1.25L Sunkist No Sugar"
        }
       ],
       "shortDescription": [
        {
         "lang": "en-US",
         "value": "1.25L Sunkist No Sugar"
        }
       ],
       "longDescription": [
        {
         "lang": "en-US",
         "value": "1.25L Sunkist No Sugar"
        }
       ],
       "imageName": [
        {
         "lang": "en-US",
         "value": "https://images.ctfassets.net/crbk84xktnsl/19s06ltECjJJZ7o0TG8YQZ/f39dc4b4326da409315f5a437866e74c/Drink_Sunkist_No_Sugar_1.25L.png"
        }
       ],
       "modgrps": [],
       "isHidden": false,
       "availability": [
        {
         "dayOfWeek": {
          "day": "EVERYDAY"
         },
         "availableHours": {
          "startTime": {
           "time": "0001"
          },
          "endTime": {
           "time": "2359"
          }
         },
         "price": 0
        }
       ],
       "effectiveStartDateTime": 0,
       "effectiveEndDateTime": 0,
       "additionalProperties": [],
       "defaultQuantity": 1,
       "isDefault": false,
       "max": 0,
       "content": {
        "entityId": "M-141017",
        "caloricValue": "25",
        "image": {
         "mainImage": "https://images.ctfassets.net/crbk84xktnsl/19s06ltECjJJZ7o0TG8YQZ/f39dc4b4326da409315f5a437866e74c/Drink_Sunkist_No_Sugar_1.25L.png",
         "secondaryImage": null,
         "tertiaryImage": null
        }
       }
      }
     ],
     "additionalProperties": [
      {
       "key": "peroptionmaximum",
       "value": "2"
      },
      {
       "key": "peroptionminimum",
       "value": "0"
      },
      {
       "key": "maxdistinctoptions",
       "value": "0"
      }
     ],
     "displayOrder": 0,
     "isHidden": false
    }
   ],
   "modgrpIds": null,
   "isHidden": false,
   "isCategoryHidden": true,
   "availability": [
    {
     "dayOfWeek": {
      "day": "EVERYDAY"
     },
     "availableHours": {
      "startTime": {
       "time": "0001"
      },
      "endTime": {
       "time": "2359"
      }
     },
     "price": 695
    }
   ],
   "isTimeSpecific": false,
   "effectiveStartDateTime": 0,
   "effectiveEndDateTime": 0,
   "additionalProperties": [
    {
     "key": "mealdealdetailid",
     "value": "MENU_ITEM"
    },
    {
     "key": "calories",
     "value": "3548"
    },
    {
     "key": "pricewithouttax",
     "value": "695"
    },
    {
     "key": "upSizeItemPrice",
     "value": "695"
    }
   ],
   "recommendationRules": [],
   "content": {
    "entityId": "I-31999",
    "caloricValue": "3548",
    "nutritionalInformation": [],
    "allergenInformation": [],
    "hideNutritionInformation": true,
    "hideAllergenInformation": true,
    "showInFactSheet": false,
    "flagText": null,
    "tagArray": [],
    "image": {
     "mainImage": "https://images.ctfassets.net/crbk84xktnsl/2nPxqj0LvYh05LxIlkdGOh/b7fc4902ea42519023a027f9a3dc2c2b/Sides_2.png",
     "secondaryImage": null,
     "tertiaryImage": null
    },
    "serves": 0
   },
   "categoryUrl": [
    "fomo-wow"
   ],
   "categoryId": "C-20069"
  }
 ],
 "additionalProperties": [
  {
   "key": "type",
   "value": "MENU_ITEM"
  }
 ],
 "displayOrder": 36,
 "isHidden": false,
 "content": {
  "entityId": "C-31999-prod",
  "caloricValue": "3548",
  "image": {
   "mainImage": "https://images.ctfassets.net/crbk84xktnsl/2nPxqj0LvYh05LxIlkdGOh/b7fc4902ea42519023a027f9a3dc2c2b/Sides_2.png",
   "secondaryImage": null,
   "tertiaryImage": null
  },
  "flagText": null,
  "tagArray": [],
  "shortDescription": null,
  "serves": 0
 },
 "url": "add-2-sides-for-695"
}