{
 "mdmId": "C-32877-prod",
 "name": "$15.95 Boneless Pack for Two",
 "id": "C-32877-prod",
 "customizable": false,
 "dname": [
  {
   "lang": "en-US",
   "value": "$15.95 Boneless Pack for Two"
  }
 ],
 "shortDescription": [
  {
   "lang": "en-US",
   "value": "20 Nuggets, 6 Original Tenders and 2 Regular Chips."
  }
 ],
 "longDescription": [
  {
   "lang": "en-US",
   "value": "20 Nuggets, 6 Original Tenders and 2 Regular Chips."
  }
 ],
 "imageName": "C-32877",
 "items": [
  {
   "mdmId": "I-32877-0",
   "id": "I-32877-0",
   "name": "$15.95 Boneless Pack for Two",
   "size": null,
   "linkId": "",
   "url": "1595-boneless-pack-for-two",
   "isPromo": false,
   "posId": "",
   "displayOrder": 0,
   "customizable": false,
   "dname": [
    {
     "lang": "en-US",
     "value": "$15.95 Boneless Pack for Two"
    }
   ],
   "shortDescription": [
    {
     "lang": "en-US",
     "value": "20 Nuggets, 6 Original Tenders and 2 Regular Chips."
    }
   ],
   "longDescription": [
    {
     "lang": "en-US",
     "value": "20 Nuggets, 6 Original Tenders and 2 Regular Chips."
    }
   ],
   "imageName": [
    {
     "lang": "en-US",
     "value": "I-32877-0"
    }
   ],
   "modgrps": [
    {
     "id": "32877-1-0",
     "name": "Nuggets",
     "dname": [
      {
       "lang": "en-US",
       "value": "Nuggets"
      }
     ],
     "min": 1,
     "max": 1,
     "shortDescription": [
      {
       "lang": "en-US",
       "value": "Nuggets"
      }
     ],
     "longDescription": [
      {
       "lang": "en-US",
       "value": "Nuggets"
      }
     ],
     "modifiers": [
      {
       "mdmId": "M-43406-0",
       "id": "M-43406-0",
       "name": "20 Nuggets",
       "size": "Regular",
       "linkId": "43406",
       "url": "20-nuggets",
       "isPromo": false,
       "posId": "184017",
       "displayOrder": 7544,
       "customizable": false,
       "dname": [
        {
         "lang": "en-US",
         "value": "20 Nuggets"
        }
       ],
       "shortDescription": [
        {
         "lang": "en-US",
         "value": "20 Nuggets"
        }
       ],
       "longDescription": [
        {
         "lang": "en-US",
         "value": "20 Nuggets"
        }
       ],
       "imageName": [
        {
         "lang": "en-US",
         "value": "https://images.ctfassets.net/crbk84xktnsl/5do1O3ca7sB7X0498oyDMT/47a91cd12a445a62228dd0b9ac224f27/20_Nuggets.png"
        }
       ],
       "modgrps": [],
       "isHidden": false,
       "availability": [
        {
         "dayOfWeek": {
          "day": "EVERYDAY"
         },
         "availableHours": {
          "startTime": {
           "time": "0001"
          },
          "endTime": {
           "time": "2359"
          }
         },
         "price": 0
        }
       ],
       "effectiveStartDateTime": 0,
       "effectiveEndDateTime": 0,
       "additionalProperties": [],
       "defaultQuantity": 1,
       "isDefault": true,
       "max": 0,
       "content": {
        "entityId": "M-43406-0",
        "caloricValue": null,
        "image": {
         "mainImage": "https://images.ctfassets.net/crbk84xktnsl/5do1O3ca7sB7X0498oyDMT/47a91cd12a445a62228dd0b9ac224f27/20_Nuggets.png",
         "secondaryImage": null,
         "tertiaryImage": null
        }
       }
      }
     ],
     "additionalProperties": [
      {
       "key": "peroptionmaximum",
       "value": "0"
      },
      {
       "key": "peroptionminimum",
       "value": "0"
      },
      {
       "key": "maxdistinctoptions",
       "value": "0"
      }
     ],
     "displayOrder": 1,
     "isHidden": false
    },
    {
     "id": "32877-2-0",
     "name": "Dipping Sauces",
     "dname": [
      {
       "lang": "en-US",
       "value": "Dipping Sauces"
      }
     ],
     "min": 1,
     "max": 1,
     "shortDescription": [
      {
       "lang": "en-US",
       "value": "Dipping Sauces"
      }
     ],
     "longDescription": [
      {
       "lang": "en-US",
       "value": "Dipping Sauces"
      }
     ],
     "modifiers": [
      {
       "mdmId": "M-43120-0",
       "id": "M-43120-0",
       "name": "2 Dipping Sauces",
       "size": "Regular",
       "linkId": "43120",
       "url": "2-dipping-sauces",
       "isPromo": false,
       "posId": "200038",
       "displayOrder": 7545,
       "customizable": false,
       "dname": [
        {
         "lang": "en-US",
         "value": "2 Dipping Sauces"
        }
       ],
       "shortDescription": [
        {
         "lang": "en-US",
         "value": "2 Dipping Sauces"
        }
       ],
       "longDescription": [
        {
         "lang": "en-US",
         "value": "2 Dipping Sauces"
        }
       ],
       "imageName": [
        {
         "lang": "en-US",
         "value": "https://images.ctfassets.net/crbk84xktnsl/0Qo5sxBsJECpZgWJ4aVXZ/f271eec1c0ddd2a8af7c302e773060b2/Sauce_Range.png"
        }
       ],
       "modgrps": [
        {
         "id": "91564",
         "name": "2 Dipping Sauces",
         "dname": [
          {
           "lang": "en-US",
           "value": "2 Dipping Sauces"
          }
         ],
         "min": 2,
         "max": 2,
         "shortDescription": [
          {
           "lang": "en-US",
           "value": "2 Dipping Sauces"
          }
         ],
         "longDescription": [
          {
           "lang": "en-US",
           "value": "2 Dipping Sauces"
          }
         ],
         "modifiers": [
          {
           "mdmId": "M-191010",
           "id": "M-191010",
           "name": "Aioli Dip",
           "size": "",
           "linkId": "mod:554507",
           "url": "aioli-dip",
           "isPromo": false,
           "posId": "191010",
           "displayOrder": 2422,
           "customizable": true,
           "dname": [
            {
             "lang": "en-US",
             "value": "Aioli Dip"
            }
           ],
           "shortDescription": [
            {
             "lang": "en-US",
             "value": "Aioli Dip"
            }
           ],
           "longDescription": [
            {
             "lang": "en-US",
             "value": "Aioli Dip"
            }
           ],
           "imageName": [
            {
             "lang": "en-US",
             "value": "https://images.ctfassets.net/crbk84xktnsl/2s80xCDE5wNxxqdJkFHOzH/846c86019dc0dd9d5c9a482b82f197ed/Sauce_Aioli.png"
            }
           ],
           "modgrps": [],
           "isHidden": false,
           "availability": [
            {
             "dayOfWeek": {
              "day": "EVERYDAY"
             },
             "availableHours": {
              "startTime": {
               "time": "0001"
              },
              "endTime": {
               "time": "2359"
              }
             },
             "price": 0
            }
           ],
           "effectiveStartDateTime": 0,
           "effectiveEndDateTime": 0,
           "additionalProperties": [],
           "defaultQuantity": 1,
           "isDefault": false,
           "max": 0,
           "content": {
            "entityId": "M-191010",
            "caloricValue": "567",
            "image": {
             "mainImage": "https://images.ctfassets.net/crbk84xktnsl/2s80xCDE5wNxxqdJkFHOzH/846c86019dc0dd9d5c9a482b82f197ed/Sauce_Aioli.png",
             "secondaryImage": null,
             "tertiaryImage": null
            }
           }
          },
          {
           "mdmId": "M-191006",
           "id": "M-191006",
           "name": "BBQ Dip",
           "size": "",
           "linkId": "mod:554508",
           "url": "bbq-dip",
           "isPromo": false,
           "posId": "191006",
           "displayOrder": 2423,
           "customizable": true,
           "dname": [
            {
             "lang": "en-US",
             "value": "BBQ Dip"
            }
           ],
           "shortDescription": [
            {
             "lang": "en-US",
             "value": "BBQ Dip"
            }
           ],
           "longDescription": [
            {
             "lang": "en-US",
             "value": "BBQ Dip"
            }
           ],
           "imageName": [
            {
             "lang": "en-US",
             "value": "https://images.ctfassets.net/crbk84xktnsl/6OIues0y1nbh86fribfI3g/f63bb86b4f66a8f5bb8d8d515fcfb23b/Sauce_BBQ.png"
            }
           ],
           "modgrps": [],
           "isHidden": false,
           "availability": [
            {
             "dayOfWeek": {
              "day": "EVERYDAY"
             },
             "availableHours": {
              "startTime": {
               "time": "0001"
              },
              "endTime": {
               "time": "2359"
              }
             },
             "price": 0
            }
           ],
           "effectiveStartDateTime": 0,
           "effectiveEndDateTime": 0,
           "additionalProperties": [],
           "defaultQuantity": 1,
           "isDefault": false,
           "max": 0,
           "content": {
            "entityId": "M-191006",
            "caloricValue": "210",
            "image": {
             "mainImage": "https://images.ctfassets.net/crbk84xktnsl/6OIues0y1nbh86fribfI3g/f63bb86b4f66a8f5bb8d8d515fcfb23b/Sauce_BBQ.png",
             "secondaryImage": null,
             "tertiaryImage": null
            }
           }
          },
          {
           "mdmId": "M-191007",
           "id": "M-191007",
           "name": "Supercharged Dip",
           "size": "",
           "linkId": "mod:554503",
           "url": "supercharged-dip",
           "isPromo": false,
           "posId": "191007",
           "displayOrder": 2424,
           "customizable": true,
           "dname": [
            {
             "lang": "en-US",
             "value": "Supercharged Dip"
            }
           ],
           "shortDescription": [
            {
             "lang": "en-US",
             "value": "Supercharged Dip"
            }
           ],
           "longDescription": [
            {
             "lang": "en-US",
             "value": "Supercharged Dip"
            }
           ],
           "imageName": [
            {
             "lang": "en-US",
             "value": "https://images.ctfassets.net/crbk84xktnsl/RLMHlsQrPIe7tyFlxrRxm/143df961b5b8b411528591d3da26beaf/Sauce_Supercharged.png"
            }
           ],
           "modgrps": [],
           "isHidden": false,
           "availability": [
            {
             "dayOfWeek": {
              "day": "EVERYDAY"
             },
             "availableHours": {
              "startTime": {
               "time": "0001"
              },
              "endTime": {
               "time": "2359"
              }
             },
             "price": 0
            }
           ],
           "effectiveStartDateTime": 0,
           "effectiveEndDateTime": 0,
           "additionalProperties": [],
           "defaultQuantity": 1,
           "isDefault": false,
           "max": 0,
           "content": {
            "entityId": "M-191007",
            "caloricValue": "440",
            "image": {
             "mainImage": "https://images.ctfassets.net/crbk84xktnsl/RLMHlsQrPIe7tyFlxrRxm/143df961b5b8b411528591d3da26beaf/Sauce_Supercharged.png",
             "secondaryImage": null,
             "tertiaryImage": null
            }
           }
          },
          {
           "mdmId": "M-191009",
           "id": "M-191009",
           "name": "Sweet & Sour Dip",
           "size": "",
           "linkId": "mod:554504",
           "url": "sweet-sour-dip",
           "isPromo": false,
           "posId": "191009",
           "displayOrder": 2425,
           "customizable": true,
           "dname": [
            {
             "lang": "en-US",
             "value": "Sweet & Sour Dip"
            }
           ],
           "shortDescription": [
            {
             "lang": "en-US",
             "value": "Sweet & Sour Dip"
            }
           ],
           "longDescription": [
            {
             "lang": "en-US",
             "value": "Sweet & Sour Dip"
            }
           ],
           "imageName": [
            {
             "lang": "en-US",
             "value": "https://images.ctfassets.net/crbk84xktnsl/7FUeehrIIAfAr6ydz0XYgj/8f23ec80424da832fc756a4e9bf54dab/Sauce_Sweet_Sour.png"
            }
           ],
           "modgrps": [],
           "isHidden": false,
           "availability": [
            {
             "dayOfWeek": {
              "day": "EVERYDAY"
             },
             "availableHours": {
              "startTime": {
               "time": "0001"
              },
              "endTime": {
               "time": "2359"
              }
             },
             "price": 0
            }
           ],
           "effectiveStartDateTime": 0,
           "effectiveEndDateTime": 0,
           "additionalProperties": [
            {
             "key": "defaultreason",
             "value": "SELECTION"
            }
           ],
           "defaultQuantity": 2,
           "isDefault": true,
           "max": 0,
           "content": {
            "entityId": "M-191009",
            "caloricValue": "274",
            "image": {
             "mainImage": "https://images.ctfassets.net/crbk84xktnsl/7FUeehrIIAfAr6ydz0XYgj/8f23ec80424da832fc756a4e9bf54dab/Sauce_Sweet_Sour.png",
             "secondaryImage": null,
             "tertiaryImage": null
            }
           }
          },
          {
           "mdmId": "M-191008",
           "id": "M-191008",
           "name": "Sweet Chilli Dip",
           "size": "",
           "linkId": "mod:554505",
           "url": "sweet-chilli-dip",
           "isPromo": false,
           "posId": "191008",
           "displayOrder": 2426,
           "customizable": true,
           "dname": [
            {
             "lang": "en-US",
             "value": "Sweet Chilli Dip"
            }
           ],
           "shortDescription": [
            {
             "lang": "en-US",
             "value": "Sweet Chilli Dip"
            }
           ],
           "longDescription": [
            {
             "lang": "en-US",
             "value": "Sweet Chilli Dip"
            }
           ],
           "imageName": [
            {
             "lang": "en-US",
             "value": "https://images.ctfassets.net/crbk84xktnsl/2m4RONrsdLf2ou0NyZdWjK/9465da2e2f4a9450a6a0f96e8f12ce8f/Sauce_Sweet_Chilli.png"
            }
           ],
           "modgrps": [],
           "isHidden": false,
           "availability": [
            {
             "dayOfWeek": {
              "day": "EVERYDAY"
             },
             "availableHours": {
              "startTime": {
               "time": "0001"
              },
              "endTime": {
               "time": "2359"
              }
             },
             "price": 0
            }
           ],
           "effectiveStartDateTime": 0,
           "effectiveEndDateTime": 0,
           "additionalProperties": [],
           "defaultQuantity": 1,
           "isDefault": false,
           "max": 0,
           "content": {
            "entityId": "M-191008",
            "caloricValue": "250",
            "image": {
             "mainImage": "https://images.ctfassets.net/crbk84xktnsl/2m4RONrsdLf2ou0NyZdWjK/9465da2e2f4a9450a6a0f96e8f12ce8f/Sauce_Sweet_Chilli.png",
             "secondaryImage": null,
             "tertiaryImage": null
            }
           }
          },
          {
           "mdmId": "M-191005",
           "id": "M-191005",
           "name": "Tomato Dip",
           "size": "",
           "linkId": "mod:554506",
           "url": "tomato-dip",
           "isPromo": false,
           "posId": "191005",
           "displayOrder": 2427,
           "customizable": true,
           "dname": [
            {
             "lang": "en-US",
             "value": "Tomato Dip"
            }
           ],
           "shortDescription": [
            {
             "lang": "en-US",
             "value": "Tomato Dip"
            }
           ],
           "longDescription": [
            {
             "lang": "en-US",
             "value": "Tomato Dip"
            }
           ],
           "imageName": [
            {
             "lang": "en-US",
             "value": "https://images.ctfassets.net/crbk84xktnsl/1J8cuucnXPg85XRtybaiqC/545271fab1f0d6de1009c0559f664c35/Sauce_Tomato.png"
            }
           ],
           "modgrps": [],
           "isHidden": false,
           "availability": [
            {
             "dayOfWeek": {
              "day": "EVERYDAY"
             },
             "availableHours": {
              "startTime": {
               "time": "0001"
              },
              "endTime": {
               "time": "2359"
              }
             },
             "price": 0
            }
           ],
           "effectiveStartDateTime": 0,
           "effectiveEndDateTime": 0,
           "additionalProperties": [],
           "defaultQuantity": 1,
           "isDefault": false,
           "max": 0,
           "content": {
            "entityId": "M-191005",
            "caloricValue": "148",
            "image": {
             "mainImage": "https://images.ctfassets.net/crbk84xktnsl/1J8cuucnXPg85XRtybaiqC/545271fab1f0d6de1009c0559f664c35/Sauce_Tomato.png",
             "secondaryImage": null,
             "tertiaryImage": null
            }
           }
          },
          {
           "mdmId": "M-191011",
           "id": "M-191011",
           "name": "No Sauce",
           "size": "",
           "linkId": "mod:554502",
           "url": "no-sauce",
           "isPromo": false,
           "posId": "191011",
           "displayOrder": 2428,
           "customizable": true,
           "dname": [
            {
             "lang": "en-US",
             "value": "No Sauce"
            }
           ],
           "shortDescription": [
            {
             "lang": "en-US",
             "value": "No Sauce"
            }
           ],
           "longDescription": [
            {
             "lang": "en-US",
             "value": "No Sauce"
            }
           ],
           "imageName": [
            {
             "lang": "en-US",
             "value": "https://images.ctfassets.net/crbk84xktnsl/7mdwN5f06AWN6F0WQEXch6/ff517b105a0a4c583e5149124f153f2d/Modifier_No_Sauce.png"
            }
           ],
           "modgrps": [],
           "isHidden": false,
           "availability": [
            {
             "dayOfWeek": {
              "day": "EVERYDAY"
             },
             "availableHours": {
              "startTime": {
               "time": "0001"
              },
              "endTime": {
               "time": "2359"
              }
             },
             "price": 0
            }
           ],
           "effectiveStartDateTime": 0,
           "effectiveEndDateTime": 0,
           "additionalProperties": [],
           "defaultQuantity": 1,
           "isDefault": false,
           "max": 0,
           "content": {
            "entityId": "M-191011",
            "caloricValue": null,
            "image": {
             "mainImage": "https://images.ctfassets.net/crbk84xktnsl/7mdwN5f06AWN6F0WQEXch6/ff517b105a0a4c583e5149124f153f2d/Modifier_No_Sauce.png",
             "secondaryImage": null,
             "tertiaryImage": null
            }
           }
          }
         ],
         "additionalProperties": [
          {
           "key": "peroptionmaximum",
           "value": "2"
          },
          {
           "key": "peroptionminimum",
           "value": "0"
          },
          {
           "key": "maxdistinctoptions",
           "value": "0"
          }
         ],
         "displayOrder": 0,
         "isHidden": false
        }
       ],
       "isHidden": false,
       "availability": [
        {
         "dayOfWeek": {
          "day": "EVERYDAY"
         },
         "availableHours": {
          "startTime": {
           "time": "0001"
          },
          "endTime": {
           "time": "2359"
          }
         },
         "price": 0
        }
       ],
       "effectiveStartDateTime": 0,
       "effectiveEndDateTime": 0,
       "additionalProperties": [],
       "defaultQuantity": 1,
       "isDefault": true,
       "max": 0,
       "content": {
        "entityId": "M-43120-0",
        "caloricValue": null,
        "image": {
         "mainImage": "https://images.ctfassets.net/crbk84xktnsl/0Qo5sxBsJECpZgWJ4aVXZ/f271eec1c0ddd2a8af7c302e773060b2/Sauce_Range.png",
         "secondaryImage": null,
         "tertiaryImage": null
        }
       }
      }
     ],
     "additionalProperties": [
      {
       "key": "peroptionmaximum",
       "value": "0"
      },
      {
       "key": "peroptionminimum",
       "value": "0"
      },
      {
       "key": "maxdistinctoptions",
       "value": "0"
      }
     ],
     "displayOrder": 2,
     "isHidden": false
    },
    {
     "id": "32877-3-0",
     "name": "First Chips",
     "dname": [
      {
       "lang": "en-US",
       "value": "First Chips"
      }
     ],
     "min": 1,
     "max": 1,
     "shortDescription": [
      {
       "lang": "en-US",
       "value": "First Chips"
      }
     ],
     "longDescription": [
      {
       "lang": "en-US",
       "value": "First Chips"
      }
     ],
     "modifiers": [
      {
       "mdmId": "M-40976-0",
       "id": "M-40976-0",
       "name": "Regular Chips",
       "size": "Regular",
       "linkId": "40976",
       "url": "regular-chips",
       "isPromo": false,
       "posId": "136005",
       "displayOrder": 7553,
       "customizable": false,
       "dname": [
        {
         "lang": "en-US",
         "value": "Regular Chips"
        }
       ],
       "shortDescription": [
        {
         "lang": "en-US",
         "value": "Regular Chips"
        }
       ],
       "longDescription": [
        {
         "lang": "en-US",
         "value": "Regular Chips"
        }
       ],
       "imageName": [
        {
         "lang": "en-US",
         "value": "https://images.ctfassets.net/crbk84xktnsl/2O0nyIhZ9zedgzvy7G2D0p/b0b92adf841fa7a4610b0f0776e53040/Chips_reg.png"
        }
       ],
       "modgrps": [
        {
         "id": "89711",
         "name": "Modify Chips",
         "dname": [
          {
           "lang": "en-US",
           "value": "Modify Chips"
          }
         ],
         "min": 0,
         "max": 1,
         "shortDescription": [
          {
           "lang": "en-US",
           "value": "Modify Chips"
          }
         ],
         "longDescription": [
          {
           "lang": "en-US",
           "value": "Modify Chips"
          }
         ],
         "modifiers": [
          {
           "mdmId": "M-200031",
           "id": "M-200031",
           "name": "Extra Salt",
           "size": "",
           "linkId": "mod:554382",
           "url": "extra-salt",
           "isPromo": false,
           "posId": "200031",
           "displayOrder": 483,
           "customizable": false,
           "dname": [
            {
             "lang": "en-US",
             "value": "Extra Salt"
            }
           ],
           "shortDescription": [
            {
             "lang": "en-US",
             "value": "Extra Salt"
            }
           ],
           "longDescription": [
            {
             "lang": "en-US",
             "value": "Extra Salt"
            }
           ],
           "imageName": [
            {
             "lang": "en-US",
             "value": "https://images.ctfassets.net/crbk84xktnsl/3AfJV4aLAtIeB68Z7zB4Ff/fa811380ff7d978fdd9a5a15d6729148/Modifier_Salt.png"
            }
           ],
           "modgrps": [],
           "isHidden": false,
           "availability": [
            {
             "dayOfWeek": {
              "day": "EVERYDAY"
             },
             "availableHours": {
              "startTime": {
               "time": "0001"
              },
              "endTime": {
               "time": "2359"
              }
             },
             "price": 0
            }
           ],
           "effectiveStartDateTime": 0,
           "effectiveEndDateTime": 0,
           "additionalProperties": [],
           "defaultQuantity": 1,
           "isDefault": false,
           "max": 0,
           "content": {
            "entityId": "M-200031",
            "caloricValue": null,
            "image": {
             "mainImage": "https://images.ctfassets.net/crbk84xktnsl/3AfJV4aLAtIeB68Z7zB4Ff/fa811380ff7d978fdd9a5a15d6729148/Modifier_Salt.png",
             "secondaryImage": null,
             "tertiaryImage": null
            }
           }
          },
          {
           "mdmId": "M-200030",
           "id": "M-200030",
           "name": "No Salt",
           "size": "",
           "linkId": "mod:554383",
           "url": "no-salt",
           "isPromo": false,
           "posId": "200030",
           "displayOrder": 484,
           "customizable": false,
           "dname": [
            {
             "lang": "en-US",
             "value": "No Salt"
            }
           ],
           "shortDescription": [
            {
             "lang": "en-US",
             "value": "No Salt"
            }
           ],
           "longDescription": [
            {
             "lang": "en-US",
             "value": "No Salt"
            }
           ],
           "imageName": [
            {
             "lang": "en-US",
             "value": "https://images.ctfassets.net/crbk84xktnsl/2szW3dpmch2lJs8eIMjyOK/10d97b060f434f03cca661499597c6c5/Modifier_No_Salt.png"
            }
           ],
           "modgrps": [],
           "isHidden": false,
           "availability": [
            {
             "dayOfWeek": {
              "day": "EVERYDAY"
             },
             "availableHours": {
              "startTime": {
               "time": "0001"
              },
              "endTime": {
               "time": "2359"
              }
             },
             "price": 0
            }
           ],
           "effectiveStartDateTime": 0,
           "effectiveEndDateTime": 0,
           "additionalProperties": [],
           "defaultQuantity": 1,
           "isDefault": false,
           "max": 0,
           "content": {
            "entityId": "M-200030",
            "caloricValue": null,
            "image": {
             "mainImage": "https://images.ctfassets.net/crbk84xktnsl/2szW3dpmch2lJs8eIMjyOK/10d97b060f434f03cca661499597c6c5/Modifier_No_Salt.png",
             "secondaryImage": null,
             "tertiaryImage": null
            }
           }
          }
         ],
         "additionalProperties": [
          {
           "key": "peroptionmaximum",
           "value": "1"
          },
          {
           "key": "peroptionminimum",
           "value": "0"
          },
          {
           "key": "maxdistinctoptions",
           "value": "1"
          }
         ],
         "displayOrder": 0,
         "isHidden": false
        }
       ],
       "isHidden": false,
       "availability": [
        {
         "dayOfWeek": {
          "day": "EVERYDAY"
         },
         "availableHours": {
          "startTime": {
           "time": "0001"
          },
          "endTime": {
           "time": "2359"
          }
         },
         "price": 0
        }
       ],
       "effectiveStartDateTime": 0,
       "effectiveEndDateTime": 0,
       "additionalProperties": [
        {
         "key": "calories",
         "value": "1169"
        }
       ],
       "defaultQuantity": 1,
       "isDefault": true,
       "max": 0,
       "content": {
        "entityId": "M-40976-0",
        "caloricValue": "1216",
        "image": {
         "mainImage": "https://images.ctfassets.net/crbk84xktnsl/2O0nyIhZ9zedgzvy7G2D0p/b0b92adf841fa7a4610b0f0776e53040/Chips_reg.png",
         "secondaryImage": null,
         "tertiaryImage": null
        }
       }
      }
     ],
     "additionalProperties": [
      {
       "key": "peroptionmaximum",
       "value": "0"
      },
      {
       "key": "peroptionminimum",
       "value": "0"
      },
      {
       "key": "maxdistinctoptions",
       "value": "0"
      }
     ],
     "displayOrder": 3,
     "isHidden": false
    },
    {
     "id": "32877-4-0",
     "name": "Second Chips",
     "dname": [
      {
       "lang": "en-US",
       "value": "Second Chips"
      }
     ],
     "min": 1,
     "max": 1,
     "shortDescription": [
      {
       "lang": "en-US",
       "value": "Second Chips"
      }
     ],
     "longDescription": [
      {
       "lang": "en-US",
       "value": "Second Chips"
      }
     ],
     "modifiers": [
      {
       "mdmId": "M-40976-0",
       "id": "M-40976-0",
       "name": "Regular Chips",
       "size": "Regular",
       "linkId": "40976",
       "url": "regular-chips",
       "isPromo": false,
       "posId": "136005",
       "displayOrder": 7556,
       "customizable": false,
       "dname": [
        {
         "lang": "en-US",
         "value": "Regular Chips"
        }
       ],
       "shortDescription": [
        {
         "lang": "en-US",
         "value": "Regular Chips"
        }
       ],
       "longDescription": [
        {
         "lang": "en-US",
         "value": "Regular Chips"
        }
       ],
       "imageName": [
        {
         "lang": "en-US",
         "value": "https://images.ctfassets.net/crbk84xktnsl/2O0nyIhZ9zedgzvy7G2D0p/b0b92adf841fa7a4610b0f0776e53040/Chips_reg.png"
        }
       ],
       "modgrps": [
        {
         "id": "89711",
         "name": "Modify Chips",
         "dname": [
          {
           "lang": "en-US",
           "value": "Modify Chips"
          }
         ],
         "min": 0,
         "max": 1,
         "shortDescription": [
          {
           "lang": "en-US",
           "value": "Modify Chips"
          }
         ],
         "longDescription": [
          {
           "lang": "en-US",
           "value": "Modify Chips"
          }
         ],
         "modifiers": [
          {
           "mdmId": "M-200031",
           "id": "M-200031",
           "name": "Extra Salt",
           "size": "",
           "linkId": "mod:554382",
           "url": "extra-salt",
           "isPromo": false,
           "posId": "200031",
           "displayOrder": 483,
           "customizable": false,
           "dname": [
            {
             "lang": "en-US",
             "value": "Extra Salt"
            }
           ],
           "shortDescription": [
            {
             "lang": "en-US",
             "value": "Extra Salt"
            }
           ],
           "longDescription": [
            {
             "lang": "en-US",
             "value": "Extra Salt"
            }
           ],
           "imageName": [
            {
             "lang": "en-US",
             "value": "https://images.ctfassets.net/crbk84xktnsl/3AfJV4aLAtIeB68Z7zB4Ff/fa811380ff7d978fdd9a5a15d6729148/Modifier_Salt.png"
            }
           ],
           "modgrps": [],
           "isHidden": false,
           "availability": [
            {
             "dayOfWeek": {
              "day": "EVERYDAY"
             },
             "availableHours": {
              "startTime": {
               "time": "0001"
              },
              "endTime": {
               "time": "2359"
              }
             },
             "price": 0
            }
           ],
           "effectiveStartDateTime": 0,
           "effectiveEndDateTime": 0,
           "additionalProperties": [],
           "defaultQuantity": 1,
           "isDefault": false,
           "max": 0,
           "content": {
            "entityId": "M-200031",
            "caloricValue": null,
            "image": {
             "mainImage": "https://images.ctfassets.net/crbk84xktnsl/3AfJV4aLAtIeB68Z7zB4Ff/fa811380ff7d978fdd9a5a15d6729148/Modifier_Salt.png",
             "secondaryImage": null,
             "tertiaryImage": null
            }
           }
          },
          {
           "mdmId": "M-200030",
           "id": "M-200030",
           "name": "No Salt",
           "size": "",
           "linkId": "mod:554383",
           "url": "no-salt",
           "isPromo": false,
           "posId": "200030",
           "displayOrder": 484,
           "customizable": false,
           "dname": [
            {
             "lang": "en-US",
             "value": "No Salt"
            }
           ],
           "shortDescription": [
            {
             "lang": "en-US",
             "value": "No Salt"
            }
           ],
           "longDescription": [
            {
             "lang": "en-US",
             "value": "No Salt"
            }
           ],
           "imageName": [
            {
             "lang": "en-US",
             "value": "https://images.ctfassets.net/crbk84xktnsl/2szW3dpmch2lJs8eIMjyOK/10d97b060f434f03cca661499597c6c5/Modifier_No_Salt.png"
            }
           ],
           "modgrps": [],
           "isHidden": false,
           "availability": [
            {
             "dayOfWeek": {
              "day": "EVERYDAY"
             },
             "availableHours": {
              "startTime": {
               "time": "0001"
              },
              "endTime": {
               "time": "2359"
              }
             },
             "price": 0
            }
           ],
           "effectiveStartDateTime": 0,
           "effectiveEndDateTime": 0,
           "additionalProperties": [],
           "defaultQuantity": 1,
           "isDefault": false,
           "max": 0,
           "content": {
            "entityId": "M-200030",
            "caloricValue": null,
            "image": {
             "mainImage": "https://images.ctfassets.net/crbk84xktnsl/2szW3dpmch2lJs8eIMjyOK/10d97b060f434f03cca661499597c6c5/Modifier_No_Salt.png",
             "secondaryImage": null,
             "tertiaryImage": null
            }
           }
          }
         ],
         "additionalProperties": [
          {
           "key": "peroptionmaximum",
           "value": "1"
          },
          {
           "key": "peroptionminimum",
           "value": "0"
          },
          {
           "key": "maxdistinctoptions",
           "value": "1"
          }
         ],
         "displayOrder": 0,
         "isHidden": false
        }
       ],
       "isHidden": false,
       "availability": [
        {
         "dayOfWeek": {
          "day": "EVERYDAY"
         },
         "availableHours": {
          "startTime": {
           "time": "0001"
          },
          "endTime": {
           "time": "2359"
          }
         },
         "price": 0
        }
       ],
       "effectiveStartDateTime": 0,
       "effectiveEndDateTime": 0,
       "additionalProperties": [
        {
         "key": "calories",
         "value": "1169"
        }
       ],
       "defaultQuantity": 1,
       "isDefault": true,
       "max": 0,
       "content": {
        "entityId": "M-40976-0",
        "caloricValue": "1216",
        "image": {
         "mainImage": "https://images.ctfassets.net/crbk84xktnsl/2O0nyIhZ9zedgzvy7G2D0p/b0b92adf841fa7a4610b0f0776e53040/Chips_reg.png",
         "secondaryImage": null,
         "tertiaryImage": null
        }
       }
      }
     ],
     "additionalProperties": [
      {
       "key": "peroptionmaximum",
       "value": "0"
      },
      {
       "key": "peroptionminimum",
       "value": "0"
      },
      {
       "key": "maxdistinctoptions",
       "value": "0"
      }
     ],
     "displayOrder": 4,
     "isHidden": false
    },
    {
     "id": "32877-5-0",
     "name": "Original Tenders™",
     "dname": [
      {
       "lang": "en-US",
       "value": "Original Tenders™"
      }
     ],
     "min": 1,
     "max": 1,
     "shortDescription": [
      {
       "lang": "en-US",
       "value": "Original Tenders™"
      }
     ],
     "longDescription": [
      {
       "lang": "en-US",
       "value": "Original Tenders™"
      }
     ],
     "modifiers": [
      {
       "mdmId": "M-43753-0",
       "id": "M-43753-0",
       "name": "6 Original Tenders™",
       "size": "Regular",
       "linkId": "43753",
       "url": "6-original-tenders",
       "isPromo": false,
       "posId": "170607",
       "displayOrder": 7559,
       "customizable": false,
       "dname": [
        {
         "lang": "en-US",
         "value": "6 Original Tenders™"
        }
       ],
       "shortDescription": [
        {
         "lang": "en-US",
         "value": "6 Original Tenders™"
        }
       ],
       "longDescription": [
        {
         "lang": "en-US",
         "value": "6 Original Tenders™"
        }
       ],
       "imageName": [
        {
         "lang": "en-US",
         "value": "M-43753-0"
        }
       ],
       "modgrps": [],
       "isHidden": false,
       "availability": [
        {
         "dayOfWeek": {
          "day": "EVERYDAY"
         },
         "availableHours": {
          "startTime": {
           "time": "0001"
          },
          "endTime": {
           "time": "2359"
          }
         },
         "price": 0
        }
       ],
       "effectiveStartDateTime": 0,
       "effectiveEndDateTime": 0,
       "additionalProperties": [],
       "defaultQuantity": 1,
       "isDefault": true,
       "max": 0,
       "content": null
      }
     ],
     "additionalProperties": [
      {
       "key": "peroptionmaximum",
       "value": "0"
      },
      {
       "key": "peroptionminimum",
       "value": "0"
      },
      {
       "key": "maxdistinctoptions",
       "value": "0"
      }
     ],
     "displayOrder": 5,
     "isHidden": false
    }
   ],
   "modgrpIds": null,
   "isHidden": false,
   "isCategoryHidden": true,
   "availability": [
    {
     "dayOfWeek": {
      "day": "EVERYDAY"
     },
     "availableHours": {
      "startTime": {
       "time": "0001"
      },
      "endTime": {
       "time": "2359"
      }
     },
     "price": 1595
    }
   ],
   "isTimeSpecific": false,
   "effectiveStartDateTime": 0,
   "effectiveEndDateTime": 0,
   "additionalProperties": [
    {
     "key": "mealdealid",
     "value": "7025"
    },
    {
     "key": "mealdealdetailid",
     "value": "QUICK_COMBO"
    },
    {
     "key": "pricewithouttax",
     "value": "1595"
    },
    {
     "key": "upSizeItemPrice",
     "value": "1595"
    }
   ],
   "recommendationRules": [],
   "content": null,
   "categoryUrl": [
    "fomo-wow"
   ],
   "categoryId": "C-20069"
  }
 ],
 "additionalProperties": [
  {
   "key": "type",
   "value": "QUICK_COMBO"
  }
 ],
 "displayOrder": 88,
 "isHidden": false,
 "content": null,
 "url": "1595-boneless-pack-for-two"
}